setup.py
distributions_gyan/Binomialdistribution.py
distributions_gyan/Gaussiandistribution.py
distributions_gyan/Generaldistribution.py
distributions_gyan/__init__.py
distributions_gyan.egg-info/PKG-INFO
distributions_gyan.egg-info/SOURCES.txt
distributions_gyan.egg-info/dependency_links.txt
distributions_gyan.egg-info/not-zip-safe
distributions_gyan.egg-info/top_level.txt